simpm/__init__.py
simpm/_utils.py
simpm/dashboard.py
simpm/dashboard_data.py
simpm/des.py
simpm/dist.py
simpm/log_cfg.py
simpm/recorder.py
simpm/runner.py
simpm-2.1.2.dist-info/licenses/LICENSE
simpm-2.1.2.dist-info/METADATA
simpm-2.1.2.dist-info/WHEEL
simpm-2.1.2.dist-info/top_level.txt
simpm-2.1.2.dist-info/RECORD
