Metadata-Version: 2.4
Name: simpm
Version: 2.1.2
Summary: SimPM (Simulation for Project Management) is a discrete-event simulation toolkit for modeling project schedules and resources (Python 3+).
Home-page: https://github.com/Project-SimPM/SimPM
Author: Naimeh Sadeghi, Pedram Elmi
Author-email: "sadeghi@kntu.ac.ir", "naima.sadeghi@gmail.com", "pedram.elmi@gmail.com"
License: MIT License
Project-URL: Documentation, https://simpm.readthedocs.io/en/latest/
Project-URL: Source, https://github.com/Project-SimPM/SimPM
Project-URL: Issues, https://github.com/Project-SimPM/SimPM/issues
Project-URL: Releases, https://github.com/Project-SimPM/SimPM/releases
Project-URL: Changelog, https://simpm.readthedocs.io/en/latest/changelog.html
Keywords: python,simpm,simulation for project management,project management,project scheduling,resource management,critical path,construction,simulation,scheduling,discrete-event simulation,documentation
Classifier: Development Status :: 5 - Production/Stable
Classifier: Environment :: Console
Classifier: Intended Audience :: Developers
Classifier: Intended Audience :: Education
Classifier: Intended Audience :: Science/Research
Classifier: License :: OSI Approved :: MIT License
Classifier: Natural Language :: English
Classifier: Operating System :: OS Independent
Classifier: Programming Language :: Python
Classifier: Programming Language :: Python :: 3
Classifier: Programming Language :: Python :: Implementation :: CPython
Classifier: Programming Language :: Python :: Implementation :: PyPy
Classifier: Topic :: Scientific/Engineering
Classifier: Topic :: Office/Business :: Scheduling
Requires-Python: >=3.6
License-File: LICENSE
Requires-Dist: simpy>=4
Requires-Dist: pandas>=1
Requires-Dist: numpy>=1
Requires-Dist: scipy>=1
Requires-Dist: matplotlib>=3
Requires-Dist: colorlog>=6
Requires-Dist: streamlit>=1.32
Requires-Dist: plotly>=5
Dynamic: license-file
